taraxa/__init__.py
taraxa/admin/__init__.py
taraxa/admin/methods.py
taraxa/admin_net/__init__.py
taraxa/admin_net/methods.py
taraxa/debug/__init__.py
taraxa/eth/__init__.py
taraxa/eth/methods.py
taraxa/jsonrpc/__init__.py
taraxa/jsonrpc/_http.py
taraxa/jsonrpc/_websocket.py
taraxa/jsonrpc/http_eth.py
taraxa/jsonrpc/http_net.py
taraxa/jsonrpc/http_taraxa.py
taraxa/jsonrpc/http_web3.py
taraxa/jsonrpc/utl.py
taraxa/net/__init__.py
taraxa/net/methods.py
taraxa/taraxa/__init__.py
taraxa/taraxa/methods.py
taraxa/test/__init__.py
taraxa/test/creat_conf.py
taraxa/test/test.py
taraxa/test/test2.py
taraxa/web3/__init__.py
taraxa/web3/eth.py
taraxa/web3/methods.py
taraxa/web3/web3.py
test/__init__.py
test/path.py
test/test_eth.py
test/test_http_eth.py
test/test_net.py
test/test_node.py
test/test_node_pytaraxa.py
test/test_node_web3.py
test/test_rpc.py
test/test_taraxa.py
test/test_web3.py
taraxa_py-0.0.6.dist-info/LICENSE
taraxa_py-0.0.6.dist-info/METADATA
taraxa_py-0.0.6.dist-info/WHEEL
taraxa_py-0.0.6.dist-info/top_level.txt
taraxa_py-0.0.6.dist-info/zip-safe
taraxa_py-0.0.6.dist-info/RECORD
